pankaj_core/__init__.py
pankaj_core/example.py
pankaj_core/utils/__init__.py
pankaj_core/utils/backup.py
pankaj_core/utils/file_organizer.py
pankaj_core/utils/json_formatter.py
pankaj_core/utils/log_monitor.py
pankaj_core/utils/system_monitor.py
pankaj_core-0.0.4.dist-info/METADATA
pankaj_core-0.0.4.dist-info/WHEEL
pankaj_core-0.0.4.dist-info/top_level.txt
pankaj_core-0.0.4.dist-info/RECORD
