Metadata-Version: 2.2
Name: pankaj_core
Version: 0.0.4
Summary: A example package for test
Author-email: Pankaj Pratap Singh <pankajsys.engg@gmail.com>
Project-URL: Homepage, https://github.com/pankajps/pankaj_core
Project-URL: Issues, https://github.com/pankajps/pankaj_core/issues
Classifier: Programming Language :: Python :: 3
Classifier: Operating System :: OS Independent
Requires-Python: >=3.8
